bittensorapi/__init__.py
bittensorapi/bittensorapi.py
bittensorapi-0.1.0.dist-info/LICENSE
bittensorapi-0.1.0.dist-info/METADATA
bittensorapi-0.1.0.dist-info/WHEEL
bittensorapi-0.1.0.dist-info/top_level.txt
bittensorapi-0.1.0.dist-info/RECORD
